pptk/LICENSE
pptk/__init__.py
pptk/_add_path.py
pptk/kdtree/__init__.py
pptk/kdtree/kdtree.so
pptk/libs/libQt5Core.so.5
pptk/libs/libQt5DBus.so.5
pptk/libs/libQt5Gui.so.5
pptk/libs/libQt5Network.so.5
pptk/libs/libQt5Widgets.so.5
pptk/libs/libQt5XcbQpa.so.5
pptk/libs/libgomp.so.1
pptk/libs/libicudata.so.56
pptk/libs/libicui18n.so.56
pptk/libs/libicuuc.so.56
pptk/libs/libtbb.so.2
pptk/libs/libtbbmalloc.so.2
pptk/libs/libz.so.1
pptk/libs/qt_plugins/platforms/libqxcb.so
pptk/libs/qt_plugins/xcbglintegrations/libqxcb-egl-integration.so
pptk/libs/qt_plugins/xcbglintegrations/libqxcb-glx-integration.so
pptk/points/__init__.py
pptk/points/expr.py
pptk/points/points.py
pptk/processing/__init__.py
pptk/processing/estimate_normals/__init__.py
pptk/processing/estimate_normals/estimate_normals.so
pptk/vfuncs/__init__.py
pptk/vfuncs/vfuncs.so
pptk/viewer/__init__.py
pptk/viewer/qt.conf
pptk/viewer/viewer
pptk/viewer/viewer.py
pptk-0.1.0.dist-info/DESCRIPTION.rst
pptk-0.1.0.dist-info/METADATA
pptk-0.1.0.dist-info/RECORD
pptk-0.1.0.dist-info/WHEEL
pptk-0.1.0.dist-info/metadata.json
pptk-0.1.0.dist-info/top_level.txt
