Metadata-Version: 2.0
Name: pptk
Version: 0.1.0
Summary: A Python package for facilitating point cloud processing.
Home-page: UNKNOWN
Author: Victor Lu
Author-email: UNKNOWN
License: MIT
Platform: UNKNOWN
Classifier: Intended Audience :: Science/Research
Classifier: Topic :: Scientific/Engineering
Classifier: License :: OSI Approved :: MIT License
Requires-Dist: numpy
